diapretty/__init__.py
diapretty/html.py
diapretty/main.py
diapretty/server/__init__.py
diapretty/server/__main__.py
diapretty/server/api.py
diapretty/templates/template.html.jinja2
diapretty-0.1.1.data/scripts/diapretty
diapretty-0.1.1.dist-info/METADATA
diapretty-0.1.1.dist-info/WHEEL
diapretty-0.1.1.dist-info/entry_points.txt
diapretty-0.1.1.dist-info/top_level.txt
diapretty-0.1.1.dist-info/RECORD
